odoo/addons/l10n_jp_country_state/README.rst
odoo/addons/l10n_jp_country_state/__init__.py
odoo/addons/l10n_jp_country_state/__manifest__.py
odoo/addons/l10n_jp_country_state/data/res_country_state.xml
odoo/addons/l10n_jp_country_state/i18n/ja.po
odoo/addons/l10n_jp_country_state/readme/CONTRIBUTORS.rst
odoo/addons/l10n_jp_country_state/readme/DESCRIPTION.rst
odoo/addons/l10n_jp_country_state/readme/INSTALL.rst
odoo/addons/l10n_jp_country_state/readme/USAGE.rst
odoo/addons/l10n_jp_country_state/static/description/icon.png
odoo/addons/l10n_jp_country_state/static/description/index.html
odoo12_addon_l10n_jp_country_state-12.0.1.0.0.dist-info/METADATA
odoo12_addon_l10n_jp_country_state-12.0.1.0.0.dist-info/RECORD
odoo12_addon_l10n_jp_country_state-12.0.1.0.0.dist-info/WHEEL
odoo12_addon_l10n_jp_country_state-12.0.1.0.0.dist-info/top_level.txt
