Metadata-Version: 2.1
Name: odoo12-addon-l10n-jp-country-state
Version: 12.0.1.0.0
Summary: Japan Country States
Home-page: https://github.com/OCA/l10n-japan
Author: Quartile Limited, Odoo Community Association (OCA)
Author-email: support@odoo-community.org
License: AGPL-3
Platform: UNKNOWN
Classifier: Programming Language :: Python
Classifier: Framework :: Odoo
Classifier: License :: OSI Approved :: GNU Affero General Public License v3
Requires-Python: >=3.5
Requires-Dist: odoo12-addon-base-country-state-translatable
Requires-Dist: odoo (<12.1dev,>=12.0a)
